pycode2seq/__init__.py
pycode2seq/inference/__init__.py
pycode2seq/inference/language.py
pycode2seq/inference/antlr/Java8Lexer.py
pycode2seq/inference/antlr/Java8Parser.py
pycode2seq/inference/antlr/KotlinLexer.py
pycode2seq/inference/antlr/KotlinParser.py
pycode2seq/inference/antlr/__init__.py
pycode2seq/inference/common/__init__.py
pycode2seq/inference/common/node.py
pycode2seq/inference/common/utils.py
pycode2seq/inference/methods/__init__.py
pycode2seq/inference/methods/extracting.py
pycode2seq/inference/methods/model.py
pycode2seq/inference/methods/splitter.py
pycode2seq/inference/methods/splitting_java.py
pycode2seq/inference/methods/splitting_kotlin.py
pycode2seq/inference/model/__init__.py
pycode2seq/inference/model/labels.py
pycode2seq/inference/model/loader.py
pycode2seq/inference/model/model.py
pycode2seq/inference/parsing/__init__.py
pycode2seq/inference/parsing/languages.py
pycode2seq/inference/parsing/parser.py
pycode2seq/inference/parsing/utils.py
pycode2seq/inference/paths/__init__.py
pycode2seq/inference/paths/extracting.py
pycode2seq/training/__init__.py
pycode2seq/training/astminer_to_code2seq.py
pycode2seq/training/combine_path.py
pycode2seq/training/combine_vocabularies.py
pycode2seq/training/expand_weights.py
pycode2seq/training/mine_projects.py
pycode2seq/training/train.py
pycode2seq-0.0.6.dist-info/LICENSE
pycode2seq-0.0.6.dist-info/METADATA
pycode2seq-0.0.6.dist-info/WHEEL
pycode2seq-0.0.6.dist-info/top_level.txt
pycode2seq-0.0.6.dist-info/RECORD
