Metadata-Version: 2.1
Name: pycode2seq
Version: 0.0.6
Summary: Inference and training for multiple languages of code2seq
Home-page: https://github.com/kisate/pycode2seq
Author: Dmitrii Kharlapenko
Author-email: dimkakha@gmail.com
License: MIT
Download-URL: https://pypi.org/project/pycode2seq/
Keywords: code2seq,pytorch,pytorch-lightning,ml4code,ml4se
Platform: UNKNOWN
Requires-Dist: torch (>=1.9.0)
Requires-Dist: torchtext (>=0.10.0)
Requires-Dist: pytorch-lightning (>=1.3.5)
Requires-Dist: code2seq (==0.0.2)
Requires-Dist: antlr4-python3-runtime (==4.8)
Requires-Dist: setuptools (>=52.0.0)
Requires-Dist: tqdm (==4.58.0)
Requires-Dist: numpy (>=1.20.1)
Requires-Dist: regex (>=2019.11.1)
Requires-Dist: omegaconf (~=2.0.6)
Requires-Dist: dataclasses (~=0.6)
Requires-Dist: requests (~=2.25.1)
